corintick/__init__.py
corintick/corintick.py
corintick/serialization.py
corintick-0.2.0.dist-info/METADATA
corintick-0.2.0.dist-info/RECORD
corintick-0.2.0.dist-info/WHEEL
corintick-0.2.0.dist-info/top_level.txt
