Metadata-Version: 2.1
Name: corintick
Version: 0.2.0
Summary: Column-based datastore for historical timeseries
Home-page: https://github.com/plugaai/corintick
Author: Gustavo Bezerra
Author-email: gusutabopb@gmail.com
License: GPL
Platform: UNKNOWN
Classifier: Intended Audience :: Developers
Classifier: Intended Audience :: Science/Research
Classifier: Intended Audience :: Financial and Insurance Industry
Classifier: Development Status :: 4 - Beta
Classifier: Programming Language :: Python :: 3.6
Classifier: Programming Language :: Python :: 3.7
Classifier: Topic :: Database
Classifier: Topic :: Database :: Front-Ends
Classifier: Topic :: Software Development :: Libraries
Requires-Python: >=3.6
Provides-Extra: test
Requires-Dist: lz4 (>=1.0.0)
Requires-Dist: pandas (>=0.23)
Requires-Dist: pymongo (>=3.6)
Requires-Dist: numpy
Requires-Dist: pytz
Requires-Dist: msgpack-python
Provides-Extra: test
Requires-Dist: pytest; extra == 'test'
Requires-Dist: pytest-cov; extra == 'test'
Requires-Dist: flake8; extra == 'test'
